pyspark_cdc/__init__.py
pyspark_cdc/capture/__init__.py
pyspark_cdc/capture/builder.py
pyspark_cdc/capture/delta.py
pyspark_cdc/capture/logger.py
pyspark_cdc/entry.py
pyspark_cdc/optimizer/__init__.py
pyspark_cdc/optimizer/cron_parser.py
pyspark_cdc/optimizer/delta_optimizer.py
pyspark_cdc/py.typed
pyspark_cdc/validator/__init__.py
pyspark_cdc/validator/validators.py
pyspark_cdc/watermark/__init__.py
pyspark_cdc/watermark/models.py
pyspark_cdc-1.0.0rc1.dist-info/METADATA
pyspark_cdc-1.0.0rc1.dist-info/WHEEL
pyspark_cdc-1.0.0rc1.dist-info/licenses/LICENSE
pyspark_cdc-1.0.0rc1.dist-info/RECORD
