Metadata-Version: 2.4
Name: pyspark-cdc
Version: 1.0.0rc1
Summary: A Python library for Change Data Capture (CDC) workflows using PySpark and Delta Lake.
License-Expression: MIT
License-File: LICENSE
Keywords: spark,pyspark,cdc,change data capture,data engineering
Author: Bitros Wang
Author-email: mopspecial@gmail.com
Requires-Python: >=3.12
Classifier: Development Status :: 5 - Production/Stable
Classifier: Intended Audience :: Developers
Classifier: Operating System :: OS Independent
Classifier: Programming Language :: Python
Classifier: Programming Language :: Python :: 3 :: Only
Classifier: Programming Language :: Python :: 3.12
Classifier: Topic :: Software Development :: Libraries :: Python Modules
Classifier: Topic :: Software Development :: Quality Assurance
Project-URL: Issues, https://github.com/Bitros/pyspark-cdc/issues
Project-URL: Repository, https://github.com/Bitros/pyspark-cdc
